README.md
setup.py
aiinpy/__init__.py
aiinpy/activation.py
aiinpy/conv.py
aiinpy/dropout.py
aiinpy/lstm.py
aiinpy/model.py
aiinpy/neat.py
aiinpy/neuroevolution.py
aiinpy/nn.py
aiinpy/pool.py
aiinpy/rnn.py
aiinpy/texttobinary.py
aiinpy.egg-info/PKG-INFO
aiinpy.egg-info/SOURCES.txt
aiinpy.egg-info/dependency_links.txt
aiinpy.egg-info/requires.txt
aiinpy.egg-info/top_level.txt