Metadata-Version: 1.0
Name: aiinpy
Version: 0.0.16
Summary: An artificial intelligence library?
Home-page: https://github.com/SeanMabli/aiinpy
Author: UNKNOWN
Author-email: UNKNOWN
License: MIT
Platform: UNKNOWN
